pyemoncms/__init__.py
pyemoncms/emoncms_client.py
pyemoncms-0.1.3.dist-info/licenses/LICENSE
pyemoncms-0.1.3.dist-info/METADATA
pyemoncms-0.1.3.dist-info/WHEEL
pyemoncms-0.1.3.dist-info/top_level.txt
pyemoncms-0.1.3.dist-info/RECORD
