Metadata-Version: 2.4
Name: pyemoncms
Version: 0.1.3
Summary: A python library to interrogate emoncms API
Home-page: https://github.com/Open-Building-Management/pyemoncms
Author: Alexandre CUER
Author-email: alexandre.cuer@wanadoo.fr
Project-URL: Bug Tracker, https://github.com/Open-Building-Management/pyemoncms/issues
Classifier: Programming Language :: Python :: 3
Classifier: License :: OSI Approved :: MIT License
Classifier: Operating System :: OS Independent
Requires-Python: >=3.9
License-File: LICENSE
Requires-Dist: aiohttp
Dynamic: author
Dynamic: author-email
Dynamic: classifier
Dynamic: description
Dynamic: description-content-type
Dynamic: home-page
Dynamic: license-file
Dynamic: project-url
Dynamic: requires-dist
Dynamic: requires-python
Dynamic: summary
